frac_blp/__init__.py
frac_blp/artificial_regressors.py
frac_blp/frac_classes.py
frac_blp/frac_nodemog.py
frac_blp/frac_utils.py
frac_blp/simulate_frac_nodemog_data.py
frac_blp/examples/__init__.py
frac_blp/examples/example_frac_nodemog.py
frac_blp-0.3.0.dist-info/METADATA
frac_blp-0.3.0.dist-info/WHEEL
frac_blp-0.3.0.dist-info/top_level.txt
frac_blp-0.3.0.dist-info/RECORD
