Metadata-Version: 2.4
Name: frac-blp
Version: 0.3.0
Summary: FRAC estimation for macro-BLP models
Requires-Python: >=3.12
Requires-Dist: numpy
Requires-Dist: scipy
Requires-Dist: bs_python_utils
Requires-Dist: pydantic>=2.12.3
Requires-Dist: pydantic-settings>=2.11.0
Requires-Dist: pandas>=2.3.3
